samplersLib/__init__.py
samplersLib/_common.py
samplersLib/kernels.py
samplersLib/samplers.py
samplersLib-2408.0.dist-info/LICENSE
samplersLib-2408.0.dist-info/METADATA
samplersLib-2408.0.dist-info/WHEEL
samplersLib-2408.0.dist-info/top_level.txt
samplersLib-2408.0.dist-info/RECORD
