Metadata-Version: 2.1
Name: samplersLib
Version: 2408.0
Summary: A samplers library for both online and offline active sampling
Home-page: https://github.com/Ahmed-Bayoumy/samplersLib
Author: Ahmed H. Bayoumy
Author-email: ahmed.bayoumy@mail.mcgill.ca
Project-URL: Bug Tracker, https://github.com/Ahmed-Bayoumy/samplersLib/issues
Classifier: Programming Language :: Python :: 3
Classifier: Programming Language :: Python :: 3 :: Only
Classifier: Programming Language :: Python :: 3.8
Classifier: Programming Language :: Python :: 3.9
Classifier: Programming Language :: Python :: 3.10
Classifier: Programming Language :: Python :: 3.11
Classifier: License :: OSI Approved :: GNU Lesser General Public License v3 (LGPLv3)
Classifier: Intended Audience :: Developers
Classifier: Operating System :: OS Independent
Requires-Python: >=3.8
License-File: LICENSE
Requires-Dist: numpy >=1.22.4
Requires-Dist: pyDOE2 >=1.3.0
Requires-Dist: scipy >=1.8.1
Requires-Dist: setuptools >=58.1.0
Requires-Dist: requests >=2.20.0
Requires-Dist: pandas
Requires-Dist: plotly >=5.14.1
Provides-Extra: testing
Requires-Dist: pytest >=6.0 ; extra == 'testing'
Requires-Dist: pytest-cov >=2.0 ; extra == 'testing'
Requires-Dist: mypy >=0.910 ; extra == 'testing'
Requires-Dist: flake8 >=3.9 ; extra == 'testing'
Requires-Dist: tox >=3.24 ; extra == 'testing'
